__init__.py
version_comparator/__init__.py
version_comparator/comparator.py
version_comparator-0.0.2.dist-info/DESCRIPTION.rst
version_comparator-0.0.2.dist-info/METADATA
version_comparator-0.0.2.dist-info/RECORD
version_comparator-0.0.2.dist-info/WHEEL
version_comparator-0.0.2.dist-info/entry_points.txt
version_comparator-0.0.2.dist-info/metadata.json
version_comparator-0.0.2.dist-info/top_level.txt
