Metadata-Version: 2.0
Name: version-comparator
Version: 0.0.2
Summary: An example package. Checks if a version is equal to, greater or less than another version
Home-page: https://github.com/pcu4dros/pedro_cuadros_test/python-version-comparator
Author: Pedro Miguel Cuadros
Author-email: pemcda@gmail.com
License: BSD-3-Clause
Project-URL: Issue Tracker, https://github.com/pcu4dros/pedro_cuadros_test/python-version-comparator/issues
Project-URL: Documentation, https://python-version-comparator.readthedocs.io/
Project-URL: Changelog, https://python-version-comparator.readthedocs.io/en/latest/changelog.html
Platform: UNKNOWN
Classifier: Development Status :: 5 - Production/Stable
Classifier: Intended Audience :: Developers
Classifier: License :: OSI Approved :: BSD License
Classifier: Operating System :: Unix
Classifier: Operating System :: POSIX
Classifier: Operating System :: Microsoft :: Windows
Classifier: Programming Language :: Python
Classifier: Programming Language :: Python :: 2.7
Classifier: Programming Language :: Python :: 3
Classifier: Programming Language :: Python :: 3.5
Classifier: Programming Language :: Python :: 3.6
Classifier: Programming Language :: Python :: 3.7
Classifier: Programming Language :: Python :: 3.8
Classifier: Programming Language :: Python :: Implementation :: CPython
Classifier: Programming Language :: Python :: Implementation :: PyPy
Classifier: Topic :: Utilities
Requires-Python: >=2.7, !=3.0.*, !=3.1.*, !=3.2.*, !=3.3.*, !=3.4.*
